Workbook

Sheet Resumen
A1: Resumen General - Control de Prestamos
A2: Dias de gracia antes de marcar Atrasado | B2: 3 | C2: Supuesto ajustable: dias extra de tolerancia sumados al ciclo de pago antes de marcar un prestamo como Atrasado.
A4: Indicador | B4: Valor
A5: Total prestado (historico) | B5: =SUM(Prestamos!D2:D400)
A6: Capital pendiente actual | B6: =SUM(Prestamos!G2:G400)
A7: Total cobrado (capital+interes) | B7: =SUM(Prestamos!H2:H400)
A8: Interes total cobrado | B8: =SUM(Prestamos!I2:I400)
A9: Prestamos activos | B9: =COUNTIFS(Prestamos!A2:A400,"<>",Prestamos!M2:M400,"<>Pagado")
A10: Prestamos atrasados | B10: =COUNTIF(Prestamos!M2:M400,"Atrasado")
A11: Prestamos pagados | B11: =COUNTIF(Prestamos!M2:M400,"Pagado")
A13: Consejo: usa el filtro (flecha en el encabezado) de la pestana Prestamos, columna Estado, para ver solo los Atrasados.

Sheet Instrucciones
A1: Control de Prestamos - Guia rapida
A3: Este libro reemplaza el registro manual de prestamos en Excel por uno con formulas automaticas.
A5: Como funciona el calculo de interes (segun lo que me indicaste):
A6: - Cada prestamo tiene su propia tasa de interes por periodo (columna Tasa en la pestana Prestamos).
A7: - Cada vez que registras un pago en la pestana Pagos, el sistema calcula el interes sobre el saldo
A8: pendiente de ESE prestamo (saldo x tasa).
A9: - Si el pago es mayor al interes, la diferencia abona a capital y el saldo baja.
A10: - Si el pago es menor o igual al interes, no se abona nada a capital ese periodo (el saldo no baja).
A11: Supuesto: el interes no cubierto NO se acumula ni genera interes sobre interes.
A13: Colores (mismo criterio en todas las pestanas):
A14: Texto azul = tu escribes aqui (dato de entrada)
A15: Texto negro = formula automatica, no la edites
... A35: montos o saldos con dinero real de por medio.

Sheet Prestamos
A1: ID Prestamo | B1: Cliente | C1: Fecha inicio | D1: Monto prestado | E1: Tasa interes (%/periodo) | F1: Frecuencia de pago | G1: Saldo pendiente | H1: Total pagado | I1: Interes cobrado | J1: Fecha ultimo pago | K1: Dias desde referencia | L1: Dias max permitidos | M1: Estado
A2: =IF(B2="","","P"&TEXT(ROW()-1,"000")) | B2: Cliente Ejemplo | C2: 2026-06-01 | D2: 100000 | E2: 0.1 | F2: Quincenal | G2: =IF(B2="","",D2-SUMIFS(Pagos!$H:$H,Pagos!$B:$B,A2)) | H2: =IF(B2="","",SUMIFS(Pagos!$E:$E,Pagos!$B:$B,A2)) | I2: =IF(B2="","",SUMIFS(Pagos!$G:$G,Pagos!$B:$B,A2)) | J2: =IF(B2="","",IF(COUNTIF(Pagos!$B:$B,A2)=0,"",_xlfn.MAXIFS(Pagos!$D:$D,Pagos!$B:$B,A2))) | K2: =IF(B2="","",IF(J2="",TODAY()-C2,TODAY()-J2)) | L2: =IF(B2="","",IF(F2="Diario",1,IF(F2="Semanal",7,IF(F2="Quincenal",15,IF(F2="Mensual",30,30))))+Resumen!$B$2) | M2: =IF(B2="","",IF(G2<=0,"Pagado",IF(K2>L2,"Atrasado","Al dia")))
A3: =IF(B3="","","P"&TEXT(ROW()-1,"000")) | G3: =IF(B3="","",D3-SUMIFS(Pagos!$H:$H,Pagos!$B:$B,A3)) | H3: =IF(B3="","",SUMIFS(Pagos!$E:$E,Pagos!$B:$B,A3)) | I3: =IF(B3="","",SUMIFS(Pagos!$G:$G,Pagos!$B:$B,A3)) | J3: =IF(B3="","",IF(COUNTIF(Pagos!$B:$B,A3)=0,"",_xlfn.MAXIFS(Pagos!$D:$D,Pagos!$B:$B,A3))) | K3: =IF(B3="","",IF(J3="",TODAY()-C3,TODAY()-J3)) | L3: =IF(B3="","",IF(F3="Diario",1,IF(F3="Semanal",7,IF(F3="Quincenal",15,IF(F3="Mensual",30,30))))+Resumen!$B$2) | M3: =IF(B3="","",IF(G3<=0,"Pagado",IF(K3>L3,"Atrasado","Al dia")))
A4: =IF(B4="","","P"&TEXT(ROW()-1,"000")) | G4: =IF(B4="","",D4-SUMIFS(Pagos!$H:$H,Pagos!$B:$B,A4)) | H4: =IF(B4="","",SUMIFS(Pagos!$E:$E,Pagos!$B:$B,A4)) | I4: =IF(B4="","",SUMIFS(Pagos!$G:$G,Pagos!$B:$B,A4)) | J4: =IF(B4="","",IF(COUNTIF(Pagos!$B:$B,A4)=0,"",_xlfn.MAXIFS(Pagos!$D:$D,Pagos!$B:$B,A4))) | K4: =IF(B4="","",IF(J4="",TODAY()-C4,TODAY()-J4)) | L4: =IF(B4="","",IF(F4="Diario",1,IF(F4="Semanal",7,IF(F4="Quincenal",15,IF(F4="Mensual",30,30))))+Resumen!$B$2) | M4: =IF(B4="","",IF(G4<=0,"Pagado",IF(K4>L4,"Atrasado","Al dia")))
A5: =IF(B5="","","P"&TEXT(ROW()-1,"000")) | G5: =IF(B5="","",D5-SUMIFS(Pagos!$H:$H,Pagos!$B:$B,A5)) | H5: =IF(B5="","",SUMIFS(Pagos!$E:$E,Pagos!$B:$B,A5)) | I5: =IF(B5="","",SUMIFS(Pagos!$G:$G,Pagos!$B:$B,A5)) | J5: =IF(B5="","",IF(COUNTIF(Pagos!$B:$B,A5)=0,"",_xlfn.MAXIFS(Pagos!$D:$D,Pagos!$B:$B,A5))) | K5: =IF(B5="","",IF(J5="",TODAY()-C5,TODAY()-J5)) | L5: =IF(B5="","",IF(F5="Diario",1,IF(F5="Semanal",7,IF(F5="Quincenal",15,IF(F5="Mensual",30,30))))+Resumen!$B$2) | M5: =IF(B5="","",IF(G5<=0,"Pagado",IF(K5>L5,"Atrasado","Al dia")))
A6: =IF(B6="","","P"&TEXT(ROW()-1,"000")) | G6: =IF(B6="","",D6-SUMIFS(Pagos!$H:$H,Pagos!$B:$B,A6)) | H6: =IF(B6="","",SUMIFS(Pagos!$E:$E,Pagos!$B:$B,A6)) | I6: =IF(B6="","",SUMIFS(Pagos!$G:$G,Pagos!$B:$B,A6)) | J6: =IF(B6="","",IF(COUNTIF(Pagos!$B:$B,A6)=0,"",_xlfn.MAXIFS(Pagos!$D:$D,Pagos!$B:$B,A6))) | K6: =IF(B6="","",IF(J6="",TODAY()-C6,TODAY()-J6)) | L6: =IF(B6="","",IF(F6="Diario",1,IF(F6="Semanal",7,IF(F6="Quincenal",15,IF(F6="Mensual",30,30))))+Resumen!$B$2) | M6: =IF(B6="","",IF(G6<=0,"Pagado",IF(K6>L6,"Atrasado","Al dia")))
A7: =IF(B7="","","P"&TEXT(ROW()-1,"000")) | G7: =IF(B7="","",D7-SUMIFS(Pagos!$H:$H,Pagos!$B:$B,A7)) | H7: =IF(B7="","",SUMIFS(Pagos!$E:$E,Pagos!$B:$B,A7)) | I7: =IF(B7="","",SUMIFS(Pagos!$G:$G,Pagos!$B:$B,A7)) | J7: =IF(B7="","",IF(COUNTIF(Pagos!$B:$B,A7)=0,"",_xlfn.MAXIFS(Pagos!$D:$D,Pagos!$B:$B,A7))) | K7: =IF(B7="","",IF(J7="",TODAY()-C7,TODAY()-J7)) | L7: =IF(B7="","",IF(F7="Diario",1,IF(F7="Semanal",7,IF(F7="Quincenal",15,IF(F7="Mensual",30,30))))+Resumen!$B$2) | M7: =IF(B7="","",IF(G7<=0,"Pagado",IF(K7>L7,"Atrasado","Al dia")))
A8: =IF(B8="","","P"&TEXT(ROW()-1,"000")) | G8: =IF(B8="","",D8-SUMIFS(Pagos!$H:$H,Pagos!$B:$B,A8)) | H8: =IF(B8="","",SUMIFS(Pagos!$E:$E,Pagos!$B:$B,A8)) | I8: =IF(B8="","",SUMIFS(Pagos!$G:$G,Pagos!$B:$B,A8)) | J8: =IF(B8="","",IF(COUNTIF(Pagos!$B:$B,A8)=0,"",_xlfn.MAXIFS(Pagos!$D:$D,Pagos!$B:$B,A8))) | K8: =IF(B8="","",IF(J8="",TODAY()-C8,TODAY()-J8)) | L8: =IF(B8="","",IF(F8="Diario",1,IF(F8="Semanal",7,IF(F8="Quincenal",15,IF(F8="Mensual",30,30))))+Resumen!$B$2) | M8: =IF(B8="","",IF(G8<=0,"Pagado",IF(K8>L8,"Atrasado","Al dia")))
A9: =IF(B9="","","P"&TEXT(ROW()-1,"000")) | G9: =IF(B9="","",D9-SUMIFS(Pagos!$H:$H,Pagos!$B:$B,A9)) | H9: =IF(B9="","",SUMIFS(Pagos!$E:$E,Pagos!$B:$B,A9)) | I9: =IF(B9="","",SUMIFS(Pagos!$G:$G,Pagos!$B:$B,A9)) | J9: =IF(B9="","",IF(COUNTIF(Pagos!$B:$B,A9)=0,"",_xlfn.MAXIFS(Pagos!$D:$D,Pagos!$B:$B,A9))) | K9: =IF(B9="","",IF(J9="",TODAY()-C9,TODAY()-J9)) | L9: =IF(B9="","",IF(F9="Diario",1,IF(F9="Semanal",7,IF(F9="Quincenal",15,IF(F9="Mensual",30,30))))+Resumen!$B$2) | M9: =IF(B9="","",IF(G9<=0,"Pagado",IF(K9>L9,"Atrasado","Al dia")))
A10: =IF(B10="","","P"&TEXT(ROW()-1,"000")) | G10: =IF(B10="","",D10-SUMIFS(Pagos!$H:$H,Pagos!$B:$B,A10)) | H10: =IF(B10="","",SUMIFS(Pagos!$E:$E,Pagos!$B:$B,A10)) | I10: =IF(B10="","",SUMIFS(Pagos!$G:$G,Pagos!$B:$B,A10)) | J10: =IF(B10="","",IF(COUNTIF(Pagos!$B:$B,A10)=0,"",_xlfn.MAXIFS(Pagos!$D:$D,Pagos!$B:$B,A10))) | K10: =IF(B10="","",IF(J10="",TODAY()-C10,TODAY()-J10)) | L10: =IF(B10="","",IF(F10="Diario",1,IF(F10="Semanal",7,IF(F10="Quincenal",15,IF(F10="Mensual",30,30))))+Resumen!$B$2) | M10: =IF(B10="","",IF(G10<=0,"Pagado",IF(K10>L10,"Atrasado","Al dia")))
A11: =IF(B11="","","P"&TEXT(ROW()-1,"000")) | G11: =IF(B11="","",D11-SUMIFS(Pagos!$H:$H,Pagos!$B:$B,A11)) | H11: =IF(B11="","",SUMIFS(Pagos!$E:$E,Pagos!$B:$B,A11)) | I11: =IF(B11="","",SUMIFS(Pagos!$G:$G,Pagos!$B:$B,A11)) | J11: =IF(B11="","",IF(COUNTIF(Pagos!$B:$B,A11)=0,"",_xlfn.MAXIFS(Pagos!$D:$D,Pagos!$B:$B,A11))) | K11: =IF(B11="","",IF(J11="",TODAY()-C11,TODAY()-J11)) | L11: =IF(B11="","",IF(F11="Diario",1,IF(F11="Semanal",7,IF(F11="Quincenal",15,IF(F11="Mensual",30,30))))+Resumen!$B$2) | M11: =IF(B11="","",IF(G11<=0,"Pagado",IF(K11>L11,"Atrasado","Al dia")))
A12: =IF(B12="","","P"&TEXT(ROW()-1,"000")) | G12: =IF(B12="","",D12-SUMIFS(Pagos!$H:$H,Pagos!$B:$B,A12)) | H12: =IF(B12="","",SUMIFS(Pagos!$E:$E,Pagos!$B:$B,A12)) | I12: =IF(B12="","",SUMIFS(Pagos!$G:$G,Pagos!$B:$B,A12)) | J12: =IF(B12="","",IF(COUNTIF(Pagos!$B:$B,A12)=0,"",_xlfn.MAXIFS(Pagos!$D:$D,Pagos!$B:$B,A12))) | K12: =IF(B12="","",IF(J12="",TODAY()-C12,TODAY()-J12)) | L12: =IF(B12="","",IF(F12="Diario",1,IF(F12="Semanal",7,IF(F12="Quincenal",15,IF(F12="Mensual",30,30))))+Resumen!$B$2) | M12: =IF(B12="","",IF(G12<=0,"Pagado",IF(K12>L12,"Atrasado","Al dia")))
A13: =IF(B13="","","P"&TEXT(ROW()-1,"000")) | G13: =IF(B13="","",D13-SUMIFS(Pagos!$H:$H,Pagos!$B:$B,A13)) | H13: =IF(B13="","",SUMIFS(Pagos!$E:$E,Pagos!$B:$B,A13)) | I13: =IF(B13="","",SUMIFS(Pagos!$G:$G,Pagos!$B:$B,A13)) | J13: =IF(B13="","",IF(COUNTIF(Pagos!$B:$B,A13)=0,"",_xlfn.MAXIFS(Pagos!$D:$D,Pagos!$B:$B,A13))) | K13: =IF(B13="","",IF(J13="",TODAY()-C13,TODAY()-J13)) | L13: =IF(B13="","",IF(F13="Diario",1,IF(F13="Semanal",7,IF(F13="Quincenal",15,IF(F13="Mensual",30,30))))+Resumen!$B$2) | M13: =IF(B13="","",IF(G13<=0,"Pagado",IF(K13>L13,"Atrasado","Al dia")))
A14: =IF(B14="","","P"&TEXT(ROW()-1,"000")) | G14: =IF(B14="","",D14-SUMIFS(Pagos!$H:$H,Pagos!$B:$B,A14)) | H14: =IF(B14="","",SUMIFS(Pagos!$E:$E,Pagos!$B:$B,A14)) | I14: =IF(B14="","",SUMIFS(Pagos!$G:$G,Pagos!$B:$B,A14)) | J14: =IF(B14="","",IF(COUNTIF(Pagos!$B:$B,A14)=0,"",_xlfn.MAXIFS(Pagos!$D:$D,Pagos!$B:$B,A14))) | K14: =IF(B14="","",IF(J14="",TODAY()-C14,TODAY()-J14)) | L14: =IF(B14="","",IF(F14="Diario",1,IF(F14="Semanal",7,IF(F14="Quincenal",15,IF(F14="Mensual",30,30))))+Resumen!$B$2) | M14: =IF(B14="","",IF(G14<=0,"Pagado",IF(K14>L14,"Atrasado","Al dia")))
... A400: =IF(B400="","","P"&TEXT(ROW()-1,"000")) | G400: =IF(B400="","",D400-SUMIFS(Pagos!$H:$H,Pagos!$B:$B,A400)) | H400: =IF(B400="","",SUMIFS(Pagos!$E:$E,Pagos!$B:$B,A400)) | I400: =IF(B400="","",SUMIFS(Pagos!$G:$G,Pagos!$B:$B,A400)) | J400: =IF(B400="","",IF(COUNTIF(Pagos!$B:$B,A400)=0,"",_xlfn.MAXIFS(Pagos!$D:$D,Pagos!$B:$B,A400))) | K400: =IF(B400="","",IF(J400="",TODAY()-C400,TODAY()-J400)) | L400: =IF(B400="","",IF(F400="Diario",1,IF(F400="Semanal",7,IF(F400="Quincenal",15,IF(F400="Mensual",30,30))))+Resumen!$B$2) | M400: =IF(B400="","",IF(G400<=0,"Pagado",IF(K400>L400,"Atrasado","Al dia")))

Sheet Pagos
A1: ID Pago | B1: ID Prestamo | C1: Cliente | D1: Fecha de pago | E1: Monto pagado | F1: Saldo anterior | G1: Interes del periodo | H1: Abono a capital | I1: Saldo nuevo
A2: =IF(B2="","","PG"&TEXT(ROW()-1,"0000")) | B2: P001 | C2: =IF(B2="","",INDEX(Prestamos!$B:$B,MATCH(B2,Prestamos!$A:$A,0))) | D2: 2026-06-15 | E2: 15000 | F2: =IF(B2="","",INDEX(Prestamos!$D:$D,MATCH(B2,Prestamos!$A:$A,0))-SUMIFS($H$1:H1,$B$1:B1,B2)) | G2: =IF(B2="","",F2*INDEX(Prestamos!$E:$E,MATCH(B2,Prestamos!$A:$A,0))) | H2: =IF(B2="","",MAX(0,E2-G2)) | I2: =IF(B2="","",F2-H2)
A3: =IF(B3="","","PG"&TEXT(ROW()-1,"0000")) | B3: P001 | C3: =IF(B3="","",INDEX(Prestamos!$B:$B,MATCH(B3,Prestamos!$A:$A,0))) | D3: 2026-06-30 | E3: 12000 | F3: =IF(B3="","",INDEX(Prestamos!$D:$D,MATCH(B3,Prestamos!$A:$A,0))-SUMIFS($H$1:H1,$B$1:B1,B3)) | G3: =IF(B3="","",F3*INDEX(Prestamos!$E:$E,MATCH(B3,Prestamos!$A:$A,0))) | H3: =IF(B3="","",MAX(0,E3-G3)) | I3: =IF(B3="","",F3-H3)
A4: =IF(B4="","","PG"&TEXT(ROW()-1,"0000")) | C4: =IF(B4="","",INDEX(Prestamos!$B:$B,MATCH(B4,Prestamos!$A:$A,0))) | F4: =IF(B4="","",INDEX(Prestamos!$D:$D,MATCH(B4,Prestamos!$A:$A,0))-SUMIFS($H$1:H1,$B$1:B1,B4)) | G4: =IF(B4="","",F4*INDEX(Prestamos!$E:$E,MATCH(B4,Prestamos!$A:$A,0))) | H4: =IF(B4="","",MAX(0,E4-G4)) | I4: =IF(B4="","",F4-H4)
A5: =IF(B5="","","PG"&TEXT(ROW()-1,"0000")) | C5: =IF(B5="","",INDEX(Prestamos!$B:$B,MATCH(B5,Prestamos!$A:$A,0))) | F5: =IF(B5="","",INDEX(Prestamos!$D:$D,MATCH(B5,Prestamos!$A:$A,0))-SUMIFS($H$1:H1,$B$1:B1,B5)) | G5: =IF(B5="","",F5*INDEX(Prestamos!$E:$E,MATCH(B5,Prestamos!$A:$A,0))) | H5: =IF(B5="","",MAX(0,E5-G5)) | I5: =IF(B5="","",F5-H5)
A6: =IF(B6="","","PG"&TEXT(ROW()-1,"0000")) | C6: =IF(B6="","",INDEX(Prestamos!$B:$B,MATCH(B6,Prestamos!$A:$A,0))) | F6: =IF(B6="","",INDEX(Prestamos!$D:$D,MATCH(B6,Prestamos!$A:$A,0))-SUMIFS($H$1:H1,$B$1:B1,B6)) | G6: =IF(B6="","",F6*INDEX(Prestamos!$E:$E,MATCH(B6,Prestamos!$A:$A,0))) | H6: =IF(B6="","",MAX(0,E6-G6)) | I6: =IF(B6="","",F6-H6)
A7: =IF(B7="","","PG"&TEXT(ROW()-1,"0000")) | C7: =IF(B7="","",INDEX(Prestamos!$B:$B,MATCH(B7,Prestamos!$A:$A,0))) | F7: =IF(B7="","",INDEX(Prestamos!$D:$D,MATCH(B7,Prestamos!$A:$A,0))-SUMIFS($H$1:H1,$B$1:B1,B7)) | G7: =IF(B7="","",F7*INDEX(Prestamos!$E:$E,MATCH(B7,Prestamos!$A:$A,0))) | H7: =IF(B7="","",MAX(0,E7-G7)) | I7: =IF(B7="","",F7-H7)
A8: =IF(B8="","","PG"&TEXT(ROW()-1,"0000")) | C8: =IF(B8="","",INDEX(Prestamos!$B:$B,MATCH(B8,Prestamos!$A:$A,0))) | F8: =IF(B8="","",INDEX(Prestamos!$D:$D,MATCH(B8,Prestamos!$A:$A,0))-SUMIFS($H$1:H1,$B$1:B1,B8)) | G8: =IF(B8="","",F8*INDEX(Prestamos!$E:$E,MATCH(B8,Prestamos!$A:$A,0))) | H8: =IF(B8="","",MAX(0,E8-G8)) | I8: =IF(B8="","",F8-H8)
A9: =IF(B9="","","PG"&TEXT(ROW()-1,"0000")) | C9: =IF(B9="","",INDEX(Prestamos!$B:$B,MATCH(B9,Prestamos!$A:$A,0))) | F9: =IF(B9="","",INDEX(Prestamos!$D:$D,MATCH(B9,Prestamos!$A:$A,0))-SUMIFS($H$1:H1,$B$1:B1,B9)) | G9: =IF(B9="","",F9*INDEX(Prestamos!$E:$E,MATCH(B9,Prestamos!$A:$A,0))) | H9: =IF(B9="","",MAX(0,E9-G9)) | I9: =IF(B9="","",F9-H9)
A10: =IF(B10="","","PG"&TEXT(ROW()-1,"0000")) | C10: =IF(B10="","",INDEX(Prestamos!$B:$B,MATCH(B10,Prestamos!$A:$A,0))) | F10: =IF(B10="","",INDEX(Prestamos!$D:$D,MATCH(B10,Prestamos!$A:$A,0))-SUMIFS($H$1:H1,$B$1:B1,B10)) | G10: =IF(B10="","",F10*INDEX(Prestamos!$E:$E,MATCH(B10,Prestamos!$A:$A,0))) | H10: =IF(B10="","",MAX(0,E10-G10)) | I10: =IF(B10="","",F10-H10)
A11: =IF(B11="","","PG"&TEXT(ROW()-1,"0000")) | C11: =IF(B11="","",INDEX(Prestamos!$B:$B,MATCH(B11,Prestamos!$A:$A,0))) | F11: =IF(B11="","",INDEX(Prestamos!$D:$D,MATCH(B11,Prestamos!$A:$A,0))-SUMIFS($H$1:H1,$B$1:B1,B11)) | G11: =IF(B11="","",F11*INDEX(Prestamos!$E:$E,MATCH(B11,Prestamos!$A:$A,0))) | H11: =IF(B11="","",MAX(0,E11-G11)) | I11: =IF(B11="","",F11-H11)
A12: =IF(B12="","","PG"&TEXT(ROW()-1,"0000")) | C12: =IF(B12="","",INDEX(Prestamos!$B:$B,MATCH(B12,Prestamos!$A:$A,0))) | F12: =IF(B12="","",INDEX(Prestamos!$D:$D,MATCH(B12,Prestamos!$A:$A,0))-SUMIFS($H$1:H1,$B$1:B1,B12)) | G12: =IF(B12="","",F12*INDEX(Prestamos!$E:$E,MATCH(B12,Prestamos!$A:$A,0))) | H12: =IF(B12="","",MAX(0,E12-G12)) | I12: =IF(B12="","",F12-H12)
A13: =IF(B13="","","PG"&TEXT(ROW()-1,"0000")) | C13: =IF(B13="","",INDEX(Prestamos!$B:$B,MATCH(B13,Prestamos!$A:$A,0))) | F13: =IF(B13="","",INDEX(Prestamos!$D:$D,MATCH(B13,Prestamos!$A:$A,0))-SUMIFS($H$1:H1,$B$1:B1,B13)) | G13: =IF(B13="","",F13*INDEX(Prestamos!$E:$E,MATCH(B13,Prestamos!$A:$A,0))) | H13: =IF(B13="","",MAX(0,E13-G13)) | I13: =IF(B13="","",F13-H13)
A14: =IF(B14="","","PG"&TEXT(ROW()-1,"0000")) | C14: =IF(B14="","",INDEX(Prestamos!$B:$B,MATCH(B14,Prestamos!$A:$A,0))) | F14: =IF(B14="","",INDEX(Prestamos!$D:$D,MATCH(B14,Prestamos!$A:$A,0))-SUMIFS($H$1:H1,$B$1:B1,B14)) | G14: =IF(B14="","",F14*INDEX(Prestamos!$E:$E,MATCH(B14,Prestamos!$A:$A,0))) | H14: =IF(B14="","",MAX(0,E14-G14)) | I14: =IF(B14="","",F14-H14)
A15: =IF(B15="","","PG"&TEXT(ROW()-1,"0000")) | C15: =IF(B15="","",INDEX(Prestamos!$B:$B,MATCH(B15,Prestamos!$A:$A,0))) | F15: =IF(B15="","",INDEX(Prestamos!$D:$D,MATCH(B15,Prestamos!$A:$A,0))-SUMIFS($H$1:H1,$B$1:B1,B15)) | G15: =IF(B15="","",F15*INDEX(Prestamos!$E:$E,MATCH(B15,Prestamos!$A:$A,0))) | H15: =IF(B15="","",MAX(0,E15-G15)) | I15: =IF(B15="","",F15-H15)
A16: =IF(B16="","","PG"&TEXT(ROW()-1,"0000")) | C16: =IF(B16="","",INDEX(Prestamos!$B:$B,MATCH(B16,Prestamos!$A:$A,0))) | F16: =IF(B16="","",INDEX(Prestamos!$D:$D,MATCH(B16,Prestamos!$A:$A,0))-SUMIFS($H$1:H1,$B$1:B1,B16)) | G16: =IF(B16="","",F16*INDEX(Prestamos!$E:$E,MATCH(B16,Prestamos!$A:$A,0))) | H16: =IF(B16="","",MAX(0,E16-G16)) | I16: =IF(B16="","",F16-H16)
A17: =IF(B17="","","PG"&TEXT(ROW()-1,"0000")) | C17: =IF(B17="","",INDEX(Prestamos!$B:$B,MATCH(B17,Prestamos!$A:$A,0))) | F17: =IF(B17="","",INDEX(Prestamos!$D:$D,MATCH(B17,Prestamos!$A:$A,0))-SUMIFS($H$1:H1,$B$1:B1,B17)) | G17: =IF(B17="","",F17*INDEX(Prestamos!$E:$E,MATCH(B17,Prestamos!$A:$A,0))) | H17: =IF(B17="","",MAX(0,E17-G17)) | I17: =IF(B17="","",F17-H17)
A18: =IF(B18="","","PG"&TEXT(ROW()-1,"0000")) | C18: =IF(B18="","",INDEX(Prestamos!$B:$B,MATCH(B18,Prestamos!$A:$A,0))) | F18: =IF(B18="","",INDEX(Prestamos!$D:$D,MATCH(B18,Prestamos!$A:$A,0))-SUMIFS($H$1:H1,$B$1:B1,B18)) | G18: =IF(B18="","",F18*INDEX(Prestamos!$E:$E,MATCH(B18,Prestamos!$A:$A,0))) | H18: =IF(B18="","",MAX(0,E18-G18)) | I18: =IF(B18="","",F18-H18)
A19: =IF(B19="","","PG"&TEXT(ROW()-1,"0000")) | C19: =IF(B19="","",INDEX(Prestamos!$B:$B,MATCH(B19,Prestamos!$A:$A,0))) | F19: =IF(B19="","",INDEX(Prestamos!$D:$D,MATCH(B19,Prestamos!$A:$A,0))-SUMIFS($H$1:H1,$B$1:B1,B19)) | G19: =IF(B19="","",F19*INDEX(Prestamos!$E:$E,MATCH(B19,Prestamos!$A:$A,0))) | H19: =IF(B19="","",MAX(0,E19-G19)) | I19: =IF(B19="","",F19-H19)
A20: =IF(B20="","","PG"&TEXT(ROW()-1,"0000")) | C20: =IF(B20="","",INDEX(Prestamos!$B:$B,MATCH(B20,Prestamos!$A:$A,0))) | F20: =IF(B20="","",INDEX(Prestamos!$D:$D,MATCH(B20,Prestamos!$A:$A,0))-SUMIFS($H$1:H1,$B$1:B1,B20)) | G20: =IF(B20="","",F20*INDEX(Prestamos!$E:$E,MATCH(B20,Prestamos!$A:$A,0))) | H20: =IF(B20="","",MAX(0,E20-G20)) | I20: =IF(B20="","",F20-H20)
A21: =IF(B21="","","PG"&TEXT(ROW()-1,"0000")) | C21: =IF(B21="","",INDEX(Prestamos!$B:$B,MATCH(B21,Prestamos!$A:$A,0))) | F21: =IF(B21="","",INDEX(Prestamos!$D:$D,MATCH(B21,Prestamos!$A:$A,0))-SUMIFS($H$1:H1,$B$1:B1,B21)) | G21: =IF(B21="","",F21*INDEX(Prestamos!$E:$E,MATCH(B21,Prestamos!$A:$A,0))) | H21: =IF(B21="","",MAX(0,E21-G21)) | I21: =IF(B21="","",F21-H21)
A22: =IF(B22="","","PG"&TEXT(ROW()-1,"0000")) | C22: =IF(B22="","",INDEX(Prestamos!$B:$B,MATCH(B22,Prestamos!$A:$A,0))) | F22: =IF(B22="","",INDEX(Prestamos!$D:$D,MATCH(B22,Prestamos!$A:$A,0))-SUMIFS($H$1:H1,$B$1:B1,B22)) | G22: =IF(B22="","",F22*INDEX(Prestamos!$E:$E,MATCH(B22,Prestamos!$A:$A,0))) | H22: =IF(B22="","",MAX(0,E22-G22)) | I22: =IF(B22="","",F22-H22)
A23: =IF(B23="","","PG"&TEXT(ROW()-1,"0000")) | C23: =IF(B23="","",INDEX(Prestamos!$B:$B,MATCH(B23,Prestamos!$A:$A,0))) | F23: =IF(B23="","",INDEX(Prestamos!$D:$D,MATCH(B23,Prestamos!$A:$A,0))-SUMIFS($H$1:H1,$B$1:B1,B23)) | G23: =IF(B23="","",F23*INDEX(Prestamos!$E:$E,MATCH(B23,Prestamos!$A:$A,0))) | H23: =IF(B23="","",MAX(0,E23-G23)) | I23: =IF(B23="","",F23-H23)
A24: =IF(B24="","","PG"&TEXT(ROW()-1,"0000")) | C24: =IF(B24="","",INDEX(Prestamos!$B:$B,MATCH(B24,Prestamos!$A:$A,0))) | F24: =IF(B24="","",INDEX(Prestamos!$D:$D,MATCH(B24,Prestamos!$A:$A,0))-SUMIFS($H$1:H1,$B$1:B1,B24)) | G24: =IF(B24="","",F24*INDEX(Prestamos!$E:$E,MATCH(B24,Prestamos!$A:$A,0))) | H24: =IF(B24="","",MAX(0,E24-G24)) | I24: =IF(B24="","",F24-H24)
A25: =IF(B25="","","PG"&TEXT(ROW()-1,"0000")) | C25: =IF(B25="","",INDEX(Prestamos!$B:$B,MATCH(B25,Prestamos!$A:$A,0))) | F25: =IF(B25="","",INDEX(Prestamos!$D:$D,MATCH(B25,Prestamos!$A:$A,0))-SUMIFS($H$1:H1,$B$1:B1,B25)) | G25: =IF(B25="","",F25*INDEX(Prestamos!$E:$E,MATCH(B25,Prestamos!$A:$A,0))) | H25: =IF(B25="","",MAX(0,E25-G25)) | I25: =IF(B25="","",F25-H25)
A26: =IF(B26="","","PG"&TEXT(ROW()-1,"0000")) | C26: =IF(B26="","",INDEX(Prestamos!$B:$B,MATCH(B26,Prestamos!$A:$A,0))) | F26: =IF(B26="","",INDEX(Prestamos!$D:$D,MATCH(B26,Prestamos!$A:$A,0))-SUMIFS($H$1:H1,$B$1:B1,B26)) | G26: =IF(B26="","",F26*INDEX(Prestamos!$E:$E,MATCH(B26,Prestamos!$A:$A,0))) | H26: =IF(B26="","",MAX(0,E26-G26)) | I26: =IF(B26="","",F26-H26)
A27: =IF(B27="","","PG"&TEXT(ROW()-1,"0000")) | C27: =IF(B27="","",INDEX(Prestamos!$B:$B,MATCH(B27,Prestamos!$A:$A,0))) | F27: =IF(B27="","",INDEX(Prestamos!$D:$D,MATCH(B27,Prestamos!$A:$A,0))-SUMIFS($H$1:H1,$B$1:B1,B27)) | G27: =IF(B27="","",F27*INDEX(Prestamos!$E:$E,MATCH(B27,Prestamos!$A:$A,0))) | H27: =IF(B27="","",MAX(0,E27-G27)) | I27: =IF(B27="","",F27-H27)
A28: =IF(B28="","","PG"&TEXT(ROW()-1,"0000")) | C28: =IF(B28="","",INDEX(Prestamos!$B:$B,MATCH(B28,Prestamos!$A:$A,0))) | F28: =IF(B28="","",INDEX(Prestamos!$D:$D,MATCH(B28,Prestamos!$A:$A,0))-SUMIFS($H$1:H1,$B$1:B1,B28)) | G28: =IF(B28="","",F28*INDEX(Prestamos!$E:$E,MATCH(B28,Prestamos!$A:$A,0))) | H28: =IF(B28="","",MAX(0,E28-G28)) | I28: =IF(B28="","",F28-H28)
A29: =IF(B29="","","PG"&TEXT(ROW()-1,"0000")) | C29: =IF(B29="","",INDEX(Prestamos!$B:$B,MATCH(B29,Prestamos!$A:$A,0))) | F29: =IF(B29="","",INDEX(Prestamos!$D:$D,MATCH(B29,Prestamos!$A:$A,0))-SUMIFS($H$1:H1,$B$1:B1,B29)) | G29: =IF(B29="","",F29*INDEX(Prestamos!$E:$E,MATCH(B29,Prestamos!$A:$A,0))) | H29: =IF(B29="","",MAX(0,E29-G29)) | I29: =IF(B29="","",F29-H29)
A30: =IF(B30="","","PG"&TEXT(ROW()-1,"0000")) | C30: =IF(B30="","",INDEX(Prestamos!$B:$B,MATCH(B30,Prestamos!$A:$A,0))) | F30: =IF(B30="","",INDEX(Prestamos!$D:$D,MATCH(B30,Prestamos!$A:$A,0))-SUMIFS($H$1:H1,$B$1:B1,B30)) | G30: =IF(B30="","",F30*INDEX(Prestamos!$E:$E,MATCH(B30,Prestamos!$A:$A,0))) | H30: =IF(B30="","",MAX(0,E30-G30)) | I30: =IF(B30="","",F30-H30)
A31: =IF(B31="","","PG"&TEXT(ROW()-1,"0000")) | C31: =IF(B31="","",INDEX(Prestamos!$B:$B,MATCH(B31,Prestamos!$A:$A,0))) | F31: =IF(B31="","",INDEX(Prestamos!$D:$D,MATCH(B31,Prestamos!$A:$A,0))-SUMIFS($H$1:H1,$B$1:B1,B31)) | G31: =IF(B31="","",F31*INDEX(Prestamos!$E:$E,MATCH(B31,Prestamos!$A:$A,0))) | H31: =IF(B31="","",MAX(0,E31-G31)) | I31: =IF(B31="","",F31-H31)
A32: =IF(B32="","","PG"&TEXT(ROW()-1,"0000")) | C32: =IF(B32="","",INDEX(Prestamos!$B:$B,MATCH(B32,Prestamos!$A:$A,0))) | F32: =IF(B32="","",INDEX(Prestamos!$D:$D,MATCH(B32,Prestamos!$A:$A,0))-SUMIFS($H$1:H1,$B$1:B1,B32)) | G32: =IF(B32="","",F32*INDEX(Prestamos!$E:$E,MATCH(B32,Prestamos!$A:$A,0))) | H32: =IF(B32="","",MAX(0,E32-G32)) | I32: =IF(B32="","",F32-H32)
A33: =IF(B33="","","PG"&TEXT(ROW()-1,"0000")) | C33: =IF(B33="","",INDEX(Prestamos!$B:$B,MATCH(B33,Prestamos!$A:$A,0))) | F33: =IF(B33="","",INDEX(Prestamos!$D:$D,MATCH(B33,Prestamos!$A:$A,0))-SUMIFS($H$1:H1,$B$1:B1,B33)) | G33: =IF(B33="","",F33*INDEX(Prestamos!$E:$E,MATCH(B33,Prestamos!$A:$A,0))) | H33: =IF(B33="","",MAX(0,E33-G33)) | I33: =IF(B33="","",F33-H33)
A34: =IF(B34="","","PG"&TEXT(ROW()-1,"0000")) | C34: =IF(B34="","",INDEX(Prestamos!$B:$B,MATCH(B34,Prestamos!$A:$A,0))) | F34: =IF(B34="","",INDEX(Prestamos!$D:$D,MATCH(B34,Prestamos!$A:$A,0))-SUMIFS($H$1:H1,$B$1:B1,B34)) | G34: =IF(B34="","",F34*INDEX(Prestamos!$E:$E,MATCH(B34,Prestamos!$A:$A,0))) | H34: =IF(B34="","",MAX(0,E34-G34)) | I34: =IF(B34="","",F34-H34)
A35: =IF(B35="","","PG"&TEXT(ROW()-1,"0000")) | C35: =IF(B35="","",INDEX(Prestamos!$B:$B,MATCH(B35,Prestamos!$A:$A,0))) | F35: =IF(B35="","",INDEX(Prestamos!$D:$D,MATCH(B35,Prestamos!$A:$A,0))-SUMIFS($H$1:H1,$B$1:B1,B35)) | G35: =IF(B35="","",F35*INDEX(Prestamos!$E:$E,MATCH(B35,Prestamos!$A:$A,0))) | H35: =IF(B35="","",MAX(0,E35-G35)) | I35: =IF(B35="","",F35-H35)
A36: =IF(B36="","","PG"&TEXT(ROW()-1,"0000")) | C36: =IF(B36="","",INDEX(Prestamos!$B:$B,MATCH(B36,Prestamos!$A:$A,0))) | F36: =IF(B36="","",INDEX(Prestamos!$D:$D,MATCH(B36,Prestamos!$A:$A,0))-SUMIFS($H$1:H1,$B$1:B1,B36)) | G36: =IF(B36="","",F36*INDEX(Prestamos!$E:$E,MATCH(B36,Prestamos!$A:$A,0))) | H36: =IF(B36="","",MAX(0,E36-G36)) | I36: =IF(B36="","",F36-H36)
A37: =IF(B37="","","PG"&TEXT(ROW()-1,"0000")) | C37: =IF(B37="","",INDEX(Prestamos!$B:$B,MATCH(B37,Prestamos!$A:$A,0))) | F37: =IF(B37="","",INDEX(Prestamos!$D:$D,MATCH(B37,Prestamos!$A:$A,0))-SUMIFS($H$1:H1,$B$1:B1,B37)) | G37: =IF(B37="","",F37*INDEX(Prestamos!$E:$E,MATCH(B37,Prestamos!$A:$A,0))) | H37: =IF(B37="","",MAX(0,E37-G37)) | I37: =IF(B37="","",F37-H37)
A38: =IF(B38="","","PG"&TEXT(ROW()-1,"0000")) | C38: =IF(B38="","",INDEX(Prestamos!$B:$B,MATCH(B38,Prestamos!$A:$A,0))) | F38: =IF(B38="","",INDEX(Prestamos!$D:$D,MATCH(B38,Prestamos!$A:$A,0))-SUMIFS($H$1:H1,$B$1:B1,B38)) | G38: =IF(B38="","",F38*INDEX(Prestamos!$E:$E,MATCH(B38,Prestamos!$A:$A,0))) | H38: =IF(B38="","",MAX(0,E38-G38)) | I38: =IF(B38="","",F38-H38)
A39: =IF(B39="","","PG"&TEXT(ROW()-1,"0000")) | C39: =IF(B39="","",INDEX(Prestamos!$B:$B,MATCH(B39,Prestamos!$A:$A,0))) | F39: =IF(B39="","",INDEX(Prestamos!$D:$D,MATCH(B39,Prestamos!$A:$A,0))-SUMIFS($H$1:H1,$B$1:B1,B39)) | G39: =IF(B39="","",F39*INDEX(Prestamos!$E:$E,MATCH(B39,Prestamos!$A:$A,0))) | H39: =IF(B39="","",MAX(0,E39-G39)) | I39: =IF(B39="","",F39-H39)
A40: =IF(B40="","","PG"&TEXT(ROW()-1,"0000")) | C40: =IF(B40="","",INDEX(Prestamos!$B:$B,MATCH(B40,Prestamos!$A:$A,0))) | F40: =IF(B40="","",INDEX(Prestamos!$D:$D,MATCH(B40,Prestamos!$A:$A,0))-SUMIFS($H$1:H1,$B$1:B1,B40)) | G40: =IF(B40="","",F40*INDEX(Prestamos!$E:$E,MATCH(B40,Prestamos!$A:$A,0))) | H40: =IF(B40="","",MAX(0,E40-G40)) | I40: =IF(B40="","",F40-H40)
A41: =IF(B41="","","PG"&TEXT(ROW()-1,"0000")) | C41: =IF(B41="","",INDEX(Prestamos!$B:$B,MATCH(B41,Prestamos!$A:$A,0))) | F41: =IF(B41="","",INDEX(Prestamos!$D:$D,MATCH(B41,Prestamos!$A:$A,0))-SUMIFS($H$1:H1,$B$1:B1,B41)) | G41: =IF(B41="","",F41*INDEX(Prestamos!$E:$E,MATCH(B41,Prestamos!$A:$A,0))) | H41: =IF(B41="","",MAX(0,E41-G41)) | I41: =IF(B41="","",F41-H41)
A42: =IF(B42="","","PG"&TEXT(ROW()-1,"0000")) | C42: =IF(B42="","",INDEX(Prestamos!$B:$B,MATCH(B42,Prestamos!$A:$A,0))) | F42: =IF(B42="","",INDEX(Prestamos!$D:$D,MATCH(B42,Prestamos!$A:$A,0))-SUMIFS($H$1:H1,$B$1:B1,B42)) | G42: =IF(B42="","",F42*INDEX(Prestamos!$E:$E,MATCH(B42,Prestamos!$A:$A,0))) | H42: =IF(B42="","",MAX(0,E42-G42)) | I42: =IF(B42="","",F42-H42)
A43: =IF(B43="","","PG"&TEXT(ROW()-1,"0000")) | C43: =IF(B43="","",INDEX(Prestamos!$B:$B,MATCH(B43,Prestamos!$A:$A,0))) | F43: =IF(B43="","",INDEX(Prestamos!$D:$D,MATCH(B43,Prestamos!$A:$A,0))-SUMIFS($H$1:H1,$B$1:B1,B43)) | G43: =IF(B43="","",F43*INDEX(Prestamos!$E:$E,MATCH(B43,Prestamos!$A:$A,0))) | H43: =IF(B43="","",MAX(0,E43-G43)) | I43: =IF(B43="","",F43-H43)
A44: =IF(B44="","","PG"&TEXT(ROW()-1,"0000")) | C44: =IF(B44="","",INDEX(Prestamos!$B:$B,MATCH(B44,Prestamos!$A:$A,0))) | F44: =IF(B44="","",INDEX(Prestamos!$D:$D,MATCH(B44,Prestamos!$A:$A,0))-SUMIFS($H$1:H1,$B$1:B1,B44)) | G44: =IF(B44="","",F44*INDEX(Prestamos!$E:$E,MATCH(B44,Prestamos!$A:$A,0))) | H44: =IF(B44="","",MAX(0,E44-G44)) | I44: =IF(B44="","",F44-H44)
A45: =IF(B45="","","PG"&TEXT(ROW()-1,"0000")) | C45: =IF(B45="","",INDEX(Prestamos!$B:$B,MATCH(B45,Prestamos!$A:$A,0))) | F45: =IF(B45="","",INDEX(Prestamos!$D:$D,MATCH(B45,Prestamos!$A:$A,0))-SUMIFS($H$1:H1,$B$1:B1,B45)) | G45: =IF(B45="","",F45*INDEX(Prestamos!$E:$E,MATCH(B45,Prestamos!$A:$A,0))) | H45: =IF(B45="","",MAX(0,E45-G45)) | I45: =IF(B45="","",F45-H45)
A46: =IF(B46="","","PG"&TEXT(ROW()-1,"0000")) | C46: =IF(B46="","",INDEX(Prestamos!$B:$B,MATCH(B46,Prestamos!$A:$A,0))) | F46: =IF(B46="","",INDEX(Prestamos!$D:$D,MATCH(B46,Prestamos!$A:$A,0))-SUMIFS($H$1:H1,$B$1:B1,B46)) | G46: =IF(B46="","",F46*INDEX(Prestamos!$E:$E,MATCH(B46,Prestamos!$A:$A,0))) | H46: =IF(B46="","",MAX(0,E46-G46)) | I46: =IF(B46="","",F46-H46)
A47: =IF(B47="","","PG"&TEXT(ROW()-1,"0000")) | C47: =IF(B47="","",INDEX(Prestamos!$B:$B,MATCH(B47,Prestamos!$A:$A,0))) | F47: =IF(B47="","",INDEX(Prestamos!$D:$D,MATCH(B47,Prestamos!$A:$A,0))-SUMIFS($H$1:H1,$B$1:B1,B47)) | G47: =IF(B47="","",F47*INDEX(Prestamos!$E:$E,MATCH(B47,Prestamos!$A:$A,0))) | H47: =IF(B47="","",MAX(0,E47-G47)) | I47: =IF(B47="","",F47-H47)
A48: =IF(B48="","","PG"&TEXT(ROW()-1,"0000")) | C48: =IF(B48="","",INDEX(Prestamos!$B:$B,MATCH(B48,Prestamos!$A:$A,0))) | F48: =IF(B48="","",INDEX(Prestamos!$D:$D,MATCH(B48,Prestamos!$A:$A,0))-SUMIFS($H$1:H1,$B$1:B1,B48)) | G48: =IF(B48="","",F48*INDEX(Prestamos!$E:$E,MATCH(B48,Prestamos!$A:$A,0))) | H48: =IF(B48="","",MAX(0,E48-G48)) | I48: =IF(B48="","",F48-H48)
A49: =IF(B49="","","PG"&TEXT(ROW()-1,"0000")) | C49: =IF(B49="","",INDEX(Prestamos!$B:$B,MATCH(B49,Prestamos!$A:$A,0))) | F49: =IF(B49="","",INDEX(Prestamos!$D:$D,MATCH(B49,Prestamos!$A:$A,0))-SUMIFS($H$1:H1,$B$1:B1,B49)) | G49: =IF(B49="","",F49*INDEX(Prestamos!$E:$E,MATCH(B49,Prestamos!$A:$A,0))) | H49: =IF(B49="","",MAX(0,E49-G49)) | I49: =IF(B49="","",F49-H49)
A50: =IF(B50="","","PG"&TEXT(ROW()-1,"0000")) | C50: =IF(B50="","",INDEX(Prestamos!$B:$B,MATCH(B50,Prestamos!$A:$A,0))) | F50: =IF(B50="","",INDEX(Prestamos!$D:$D,MATCH(B50,Prestamos!$A:$A,0))-SUMIFS($H$1:H1,$B$1:B1,B50)) | G50: =IF(B50="","",F50*INDEX(Prestamos!$E:$E,MATCH(B50,Prestamos!$A:$A,0))) | H50: =IF(B50="","",MAX(0,E50-G50)) | I50: =IF(B50="","",F50-H50)
A51: =IF(B51="","","PG"&TEXT(ROW()-1,"0000")) | C51: =IF(B51="","",INDEX(Prestamos!$B:$B,MATCH(B51,Prestamos!$A:$A,0))) | F51: =IF(B51="","",INDEX(Prestamos!$D:$D,MATCH(B51,Prestamos!$A:$A,0))-SUMIFS($H$1:H1,$B$1:B1,B51)) | G51: =IF(B51="","",F51*INDEX(Prestamos!$E:$E,MATCH(B51,Prestamos!$A:$A,0))) | H51: =IF(B51="","",MAX(0,E51-G51)) | I51: =IF(B51="","",F51-H51)
A52: =IF(B52="","","PG"&TEXT(ROW()-1,"0000")) | C52: =IF(B52="","",INDEX(Prestamos!$B:$B,MATCH(B52,Prestamos!$A:$A,0))) | F52: =IF(B52="","",INDEX(Prestamos!$D:$D,MATCH(B52,Prestamos!$A:$A,0))-SUMIFS($H$1:H1,$B$1:B1,B52)) | G52: =IF(B52="","",F52*INDEX(Prestamos!$E:$E,MATCH(B52,Prestamos!$A:$A,0))) | H52: =IF(B52="","",MAX(0,E52-G52)) | I52: =IF(B52="","",F52-H52)
A53: =IF(B53="","","PG"&TEXT(ROW()-1,"0000")) | C53: =IF(B53="","",INDEX(Prestamos!$B:$B,MATCH(B53,Prestamos!$A:$A,0))) | F53: =IF(B53="","",INDEX(Prestamos!$D:$D,MATCH(B53,Prestamos!$A:$A,0))-SUMIFS($H$1:H1,$B$1:B1,B53)) | G53: =IF(B53="","",F53*INDEX(Prestamos!$E:$E,MATCH(B53,Prestamos!$A:$A,0))) | H53: =IF(B53="","",MAX(0,E53-G53)) | I53: =IF(B53="","",F53-H53)
A54: =IF(B54="","","PG"&TEXT(ROW()-1,"0000")) | C54: =IF(B54="","",INDEX(Prestamos!$B:$B,MATCH(B54,Prestamos!$A:$A,0))) | F54: =IF(B54="","",INDEX(Prestamos!$D:$D,MATCH(B54,Prestamos!$A:$A,0))-SUMIFS($H$1:H1,$B$1:B1,B54)) | G54: =IF(B54="","",F54*INDEX(Prestamos!$E:$E,MATCH(B54,Prestamos!$A:$A,0))) | H54: =IF(B54="","",MAX(0,E54-G54)) | I54: =IF(B54="","",F54-H54)
A55: =IF(B55="","","PG"&TEXT(ROW()-1,"0000")) | C55: =IF(B55="","",INDEX(Prestamos!$B:$B,MATCH(B55,Prestamos!$A:$A,0))) | F55: =IF(B55="","",INDEX(Prestamos!$D:$D,MATCH(B55,Prestamos!$A:$A,0))-SUMIFS($H$1:H1,$B$1:B1,B55)) | G55: =IF(B55="","",F55*INDEX(Prestamos!$E:$E,MATCH(B55,Prestamos!$A:$A,0))) | H55: =IF(B55="","",MAX(0,E55-G55)) | I55: =IF(B55="","",F55-H55)
A56: =IF(B56="","","PG"&TEXT(ROW()-1,"0000")) | C56: =IF(B56="","",INDEX(Prestamos!$B:$B,MATCH(B56,Prestamos!$A:$A,0))) | F56: =IF(B56="","",INDEX(Prestamos!$D:$D,MATCH(B56,Prestamos!$A:$A,0))-SUMIFS($H$1:H1,$B$1:B1,B56)) | G56: =IF(B56="","",F56*INDEX(Prestamos!$E:$E,MATCH(B56,Prestamos!$A:$A,0))) | H56: =IF(B56="","",MAX(0,E56-G56)) | I56: =IF(B56="","",F56-H56)
A57: =IF(B57="","","PG"&TEXT(ROW()-1,"0000")) | C57: =IF(B57="","",INDEX(Prestamos!$B:$B,MATCH(B57,Prestamos!$A:$A,0))) | F57: =IF(B57="","",INDEX(Prestamos!$D:$D,MATCH(B57,Prestamos!$A:$A,0))-SUMIFS($H$1:H1,$B$1:B1,B57)) | G57: =IF(B57="","",F57*INDEX(Prestamos!$E:$E,MATCH(B57,Prestamos!$A:$A,0))) | H57: =IF(B57="","",MAX(0,E57-G57)) | I57: =IF(B57="","",F57-H57)
A58: =IF(B58="","","PG"&TEXT(ROW()-1,"0000")) | C58: =IF(B58="","",INDEX(Prestamos!$B:$B,MATCH(B58,Prestamos!$A:$A,0))) | F58: =IF(B58="","",INDEX(Prestamos!$D:$D,MATCH(B58,Prestamos!$A:$A,0))-SUMIFS($H$1:H1,$B$1:B1,B58)) | G58: =IF(B58="","",F58*INDEX(Prestamos!$E:$E,MATCH(B58,Prestamos!$A:$A,0))) | H58: =IF(B58="","",MAX(0,E58-G58)) | I58: =IF(B58="","",F58-H58)
A59: =IF(B59="","","PG"&TEXT(ROW()-1,"0000")) | C59: =IF(B59="","",INDEX(Prestamos!$B:$B,MATCH(B59,Prestamos!$A:$A,0))) | F59: =IF(B59="","",INDEX(Prestamos!$D:$D,MATCH(B59,Prestamos!$A:$A,0))-SUMIFS($H$1:H1,$B$1:B1,B59)) | G59: =IF(B59="","",F59*INDEX(Prestamos!$E:$E,MATCH(B59,Prestamos!$A:$A,0))) | H59: =IF(B59="","",MAX(0,E59-G59)) | I59: =IF(B59="","",F59-H59)
A60: =IF(B60="","","PG"&TEXT(ROW()-1,"0000")) | C60: =IF(B60="","",INDEX(Prestamos!$B:$B,MATCH(B60,Prestamos!$A:$A,0))) | F60: =IF(B60="","",INDEX(Prestamos!$D:$D,MATCH(B60,Prestamos!$A:$A,0))-SUMIFS($H$1:H1,$B$1:B1,B60)) | G60: =IF(B60="","",F60*INDEX(Prestamos!$E:$E,MATCH(B60,Prestamos!$A:$A,0))) | H60: =IF(B60="","",MAX(0,E60-G60)) | I60: =IF(B60="","",F60-H60)
A61: =IF(B61="","","PG"&TEXT(ROW()-1,"0000")) | C61: =IF(B61="","",INDEX(Prestamos!$B:$B,MATCH(B61,Prestamos!$A:$A,0))) | F61: =IF(B61="","",INDEX(Prestamos!$D:$D,MATCH(B61,Prestamos!$A:$A,0))-SUMIFS($H$1:H1,$B$1:B1,B61)) | G61: =IF(B61="","",F61*INDEX(Prestamos!$E:$E,MATCH(B61,Prestamos!$A:$A,0))) | H61: =IF(B61="","",MAX(0,E61-G61)) | I61: =IF(B61="","",F61-H61)
A62: =IF(B62="","","PG"&TEXT(ROW()-1,"0000")) | C62: =IF(B62="","",INDEX(Prestamos!$B:$B,MATCH(B62,Prestamos!$A:$A,0))) | F62: =IF(B62="","",INDEX(Prestamos!$D:$D,MATCH(B62,Prestamos!$A:$A,0))-SUMIFS($H$1:H1,$B$1:B1,B62)) | G62: =IF(B62="","",F62*INDEX(Prestamos!$E:$E,MATCH(B62,Prestamos!$A:$A,0))) | H62: =IF(B62="","",MAX(0,E62-G62)) | I62: =IF(B62="","",F62-H62)
A63: =IF(B63="","","PG"&TEXT(ROW()-1,"0000")) | C63: =IF(B63="","",INDEX(Prestamos!$B:$B,MATCH(B63,Prestamos!$A:$A,0))) | F63: =IF(B63="","",INDEX(Prestamos!$D:$D,MATCH(B63,Prestamos!$A:$A,0))-SUMIFS($H$1:H1,$B$1:B1,B63)) | G63: =IF(B63="","",F63*INDEX(Prestamos!$E:$E,MATCH(B63,Prestamos!$A:$A,0))) | H63: =IF(B63="","",MAX(0,E63-G63)) | I63: =IF(B63="","",F63-H63)
A64: =IF(B64="","","PG"&TEXT(ROW()-1,"0000")) | C64: =IF(B64="","",INDEX(Prestamos!$B:$B,MATCH(B64,Prestamos!$A:$A,0))) | F64: =IF(B64="","",INDEX(Prestamos!$D:$D,MATCH(B64,Prestamos!$A:$A,0))-SUMIFS($H$1:H1,$B$1:B1,B64)) | G64: =IF(B64="","",F64*INDEX(Prestamos!$E:$E,MATCH(B64,Prestamos!$A:$A,0))) | H64: =IF(B64="","",MAX(0,E64-G64)) | I64: =IF(B64="","",F64-H64)
A65: =IF(B65="","","PG"&TEXT(ROW()-1,"0000")) | C65: =IF(B65="","",INDEX(Prestamos!$B:$B,MATCH(B65,Prestamos!$A:$A,0))) | F65: =IF(B65="","",INDEX(Prestamos!$D:$D,MATCH(B65,Prestamos!$A:$A,0))-SUMIFS($H$1:H1,$B$1:B1,B65)) | G65: =IF(B65="","",F65*INDEX(Prestamos!$E:$E,MATCH(B65,Prestamos!$A:$A,0))) | H65: =IF(B65="","",MAX(0,E65-G65)) | I65: =IF(B65="","",F65-H65)
A66: =IF(B66="","","PG"&TEXT(ROW()-1,"0000")) | C66: =IF(B66="","",INDEX(Prestamos!$B:$B,MATCH(B66,Prestamos!$A:$A,0))) | F66: =IF(B66="","",INDEX(Prestamos!$D:$D,MATCH(B66,Prestamos!$A:$A,0))-SUMIFS($H$1:H1,$B$1:B1,B66)) | G66: =IF(B66="","",F66*INDEX(Prestamos!$E:$E,MATCH(B66,Prestamos!$A:$A,0))) | H66: =IF(B66="","",MAX(0,E66-G66)) | I66: =IF(B66="","",F66-H66)
A67: =IF(B67="","","PG"&TEXT(ROW()-1,"0000")) | C67: =IF(B67="","",INDEX(Prestamos!$B:$B,MATCH(B67,Prestamos!$A:$A,0))) | F67: =IF(B67="","",INDEX(Prestamos!$D:$D,MATCH(B67,Prestamos!$A:$A,0))-SUMIFS($H$1:H1,$B$1:B1,B67)) | G67: =IF(B67="","",F67*INDEX(Prestamos!$E:$E,MATCH(B67,Prestamos!$A:$A,0))) | H67: =IF(B67="","",MAX(0,E67-G67)) | I67: =IF(B67="","",F67-H67)
A68: =IF(B68="","","PG"&TEXT(ROW()-1,"0000")) | C68: =IF(B68="","",INDEX(Prestamos!$B:$B,MATCH(B68,Prestamos!$A:$A,0))) | F68: =IF(B68="","",INDEX(Prestamos!$D:$D,MATCH(B68,Prestamos!$A:$A,0))-SUMIFS($H$1:H1,$B$1:B1,B68)) | G68: =IF(B68="","",F68*INDEX(Prestamos!$E:$E,MATCH(B68,Prestamos!$A:$A,0))) | H68: =IF(B68="","",MAX(0,E68-G68)) | I68: =IF(B68="","",F68-H68)
A69: =IF(B69="","","PG"&TEXT(ROW()-1,"0000")) | C69: =IF(B69="","",INDEX(Prestamos!$B:$B,MATCH(B69,Prestamos!$A:$A,0))) | F69: =IF(B69="","",INDEX(Prestamos!$D:$D,MATCH(B69,Prestamos!$A:$A,0))-SUMIFS($H$1:H1,$B$1:B1,B69)) | G69: =IF(B69="","",F69*INDEX(Prestamos!$E:$E,MATCH(B69,Prestamos!$A:$A,0))) | H69: =IF(B69="","",MAX(0,E69-G69)) | I69: =IF(B69="","",F69-H69)
A70: =IF(B70="","","PG"&TEXT(ROW()-1,"0000")) | C70: =IF(B70="","",INDEX(Prestamos!$B:$B,MATCH(B70,Prestamos!$A:$A,0))) | F70: =IF(B70="","",INDEX(Prestamos!$D:$D,MATCH(B70,Prestamos!$A:$A,0))-SUMIFS($H$1:H1,$B$1:B1,B70)) | G70: =IF(B70="","",F70*INDEX(Prestamos!$E:$E,MATCH(B70,Prestamos!$A:$A,0))) | H70: =IF(B70="","",MAX(0,E70-G70)) | I70: =IF(B70="","",F70-H70)
A71: =IF(B71="","","PG"&TEXT(ROW()-1,"0000")) | C71: =IF(B71="","",INDEX(Prestamos!$B:$B,MATCH(B71,Prestamos!$A:$A,0))) | F71: =IF(B71="","",INDEX(Prestamos!$D:$D,MATCH(B71,Prestamos!$A:$A,0))-SUMIFS($H$1:H1,$B$1:B1,B71)) | G71: =IF(B71="","",F71*INDEX(Prestamos!$E:$E,MATCH(B71,Prestamos!$A:$A,0))) | H71: =IF(B71="","",MAX(0,E71-G71)) | I71: =IF(B71="","",F71-H71)
A72: =IF(B72="","","PG"&TEXT(ROW()-1,"0000")) | C72: =IF(B72="","",INDEX(Prestamos!$B:$B,MATCH(B72,Prestamos!$A:$A,0))) | F72: =IF(B72="","",INDEX(Prestamos!$D:$D,MATCH(B72,Prestamos!$A:$A,0))-SUMIFS($H$1:H1,$B$1:B1,B72)) | G72: =IF(B72="","",F72*INDEX(Prestamos!$E:$E,MATCH(B72,Prestamos!$A:$A,0))) | H72: =IF(B72="","",MAX(0,E72-G72)) | I72: =IF(B72="","",F72-H72)
A73: =IF(B73="","","PG"&TEXT(ROW()-1,"0000")) | C73: =IF(B73="","",INDEX(Prestamos!$B:$B,MATCH(B73,Prestamos!$A:$A,0))) | F73: =IF(B73="","",INDEX(Prestamos!$D:$D,MATCH(B73,Prestamos!$A:$A,0))-SUMIFS($H$1:H1,$B$1:B1,B73)) | G73: =IF(B73="","",F73*INDEX(Prestamos!$E:$E,MATCH(B73,Prestamos!$A:$A,0))) | H73: =IF(B73="","",MAX(0,E73-G73)) | I73: =IF(B73="","",F73-H73)
A74: =IF(B74="","","PG"&TEXT(ROW()-1,"0000")) | C74: =IF(B74="","",INDEX(Prestamos!$B:$B,MATCH(B74,Prestamos!$A:$A,0))) | F74: =IF(B74="","",INDEX(Prestamos!$D:$D,MATCH(B74,Prestamos!$A:$A,0))-SUMIFS($H$1:H1,$B$1:B1,B74)) | G74: =IF(B74="","",F74*INDEX(Prestamos!$E:$E,MATCH(B74,Prestamos!$A:$A,0))) | H74: =IF(B74="","",MAX(0,E74-G74)) | I74: =IF(B74="","",F74-H74)
A75: =IF(B75="","","PG"&TEXT(ROW()-1,"0000")) | C75: =IF(B75="","",INDEX(Prestamos!$B:$B,MATCH(B75,Prestamos!$A:$A,0))) | F75: =IF(B75="","",INDEX(Prestamos!$D:$D,MATCH(B75,Prestamos!$A:$A,0))-SUMIFS($H$1:H1,$B$1:B1,B75)) | G75: =IF(B75="","",F75*INDEX(Prestamos!$E:$E,MATCH(B75,Prestamos!$A:$A,0))) | H75: =IF(B75="","",MAX(0,E75-G75)) | I75: =IF(B75="","",F75-H75)
A76: =IF(B76="","","PG"&TEXT(ROW()-1,"0000")) | C76: =IF(B76="","",INDEX(Prestamos!$B:$B,MATCH(B76,Prestamos!$A:$A,0))) | F76: =IF(B76="","",INDEX(Prestamos!$D:$D,MATCH(B76,Prestamos!$A:$A,0))-SUMIFS($H$1:H1,$B$1:B1,B76)) | G76: =IF(B76="","",F76*INDEX(Prestamos!$E:$E,MATCH(B76,Prestamos!$A:$A,0))) | H76: =IF(B76="","",MAX(0,E76-G76)) | I76: =IF(B76="","",F76-H76)
A77: =IF(B77="","","PG"&TEXT(ROW()-1,"0000")) | C77: =IF(B77="","",INDEX(Prestamos!$B:$B,MATCH(B77,Prestamos!$A:$A,0))) | F77: =IF(B77="","",INDEX(Prestamos!$D:$D,MATCH(B77,Prestamos!$A:$A,0))-SUMIFS($H$1:H1,$B$1:B1,B77)) | G77: =IF(B77="","",F77*INDEX(Prestamos!$E:$E,MATCH(B77,Prestamos!$A:$A,0))) | H77: =IF(B77="","",MAX(0,E77-G77)) | I77: =IF(B77="","",F77-H77)
A78: =IF(B78="","","PG"&TEXT(ROW()-1,"0000")) | C78: =IF(B78="","",INDEX(Prestamos!$B:$B,MATCH(B78,Prestamos!$A:$A,0))) | F78: =IF(B78="","",INDEX(Prestamos!$D:$D,MATCH(B78,Prestamos!$A:$A,0))-SUMIFS($H$1:H1,$B$1:B1,B78)) | G78: =IF(B78="","",F78*INDEX(Prestamos!$E:$E,MATCH(B78,Prestamos!$A:$A,0))) | H78: =IF(B78="","",MAX(0,E78-G78)) | I78: =IF(B78="","",F78-H78)
A79: =IF(B79="","","PG"&TEXT(ROW()-1,"0000")) | C79: =IF(B79="","",INDEX(Prestamos!$B:$B,MATCH(B79,Prestamos!$A:$A,0))) | F79: =IF(B79="","",INDEX(Prestamos!$D:$D,MATCH(B79,Prestamos!$A:$A,0))-SUMIFS($H$1:H1,$B$1:B1,B79)) | G79: =IF(B79="","",F79*INDEX(Prestamos!$E:$E,MATCH(B79,Prestamos!$A:$A,0))) | H79: =IF(B79="","",MAX(0,E79-G79)) | I79: =IF(B79="","",F79-H79)
A80: =IF(B80="","","PG"&TEXT(ROW()-1,"0000")) | C80: =IF(B80="","",INDEX(Prestamos!$B:$B,MATCH(B80,Prestamos!$A:$A,0))) | F80: =IF(B80="","",INDEX(Prestamos!$D:$D,MATCH(B80,Prestamos!$A:$A,0))-SUMIFS($H$1:H1,$B$1:B1,B80)) | G80: =IF(B80="","",F80*INDEX(Prestamos!$E:$E,MATCH(B80,Prestamos!$A:$A,0))) | H80: =IF(B80="","",MAX(0,E80-G80)) | I80: =IF(B80="","",F80-H80)
A81: =IF(B81="","","PG"&TEXT(ROW()-1,"0000")) | C81: =IF(B81="","",INDEX(Prestamos!$B:$B,MATCH(B81,Prestamos!$A:$A,0))) | F81: =IF(B81="","",INDEX(Prestamos!$D:$D,MATCH(B81,Prestamos!$A:$A,0))-SUMIFS($H$1:H1,$B$1:B1,B81)) | G81: =IF(B81="","",F81*INDEX(Prestamos!$E:$E,MATCH(B81,Prestamos!$A:$A,0))) | H81: =IF(B81="","",MAX(0,E81-G81)) | I81: =IF(B81="","",F81-H81)
A82: =IF(B82="","","PG"&TEXT(ROW()-1,"0000")) | C82: =IF(B82="","",INDEX(Prestamos!$B:$B,MATCH(B82,Prestamos!$A:$A,0))) | F82: =IF(B82="","",INDEX(Prestamos!$D:$D,MATCH(B82,Prestamos!$A:$A,0))-SUMIFS($H$1:H1,$B$1:B1,B82)) | G82: =IF(B82="","",F82*INDEX(Prestamos!$E:$E,MATCH(B82,Prestamos!$A:$A,0))) | H82: =IF(B82="","",MAX(0,E82-G82)) | I82: =IF(B82="","",F82-H82)
A83: =IF(B83="","","PG"&TEXT(ROW()-1,"0000")) | C83: =IF(B83="","",INDEX(Prestamos!$B:$B,MATCH(B83,Prestamos!$A:$A,0))) | F83: =IF(B83="","",INDEX(Prestamos!$D:$D,MATCH(B83,Prestamos!$A:$A,0))-SUMIFS($H$1:H1,$B$1:B1,B83)) | G83: =IF(B83="","",F83*INDEX(Prestamos!$E:$E,MATCH(B83,Prestamos!$A:$A,0))) | H83: =IF(B83="","",MAX(0,E83-G83)) | I83: =IF(B83="","",F83-H83)
A84: =IF(B84="","","PG"&TEXT(ROW()-1,"0000")) | C84: =IF(B84="","",INDEX(Prestamos!$B:$B,MATCH(B84,Prestamos!$A:$A,0))) | F84: =IF(B84="","",INDEX(Prestamos!$D:$D,MATCH(B84,Prestamos!$A:$A,0))-SUMIFS($H$1:H1,$B$1:B1,B84)) | G84: =IF(B84="","",F84*INDEX(Prestamos!$E:$E,MATCH(B84,Prestamos!$A:$A,0))) | H84: =IF(B84="","",MAX(0,E84-G84)) | I84: =IF(B84="","",F84-H84)
A85: =IF(B85="","","PG"&TEXT(ROW()-1,"0000")) | C85: =IF(B85="","",INDEX(Prestamos!$B:$B,MATCH(B85,Prestamos!$A:$A,0))) | F85: =IF(B85="","",INDEX(Prestamos!$D:$D,MATCH(B85,Prestamos!$A:$A,0))-SUMIFS($H$1:H1,$B$1:B1,B85)) | G85: =IF(B85="","",F85*INDEX(Prestamos!$E:$E,MATCH(B85,Prestamos!$A:$A,0))) | H85: =IF(B85="","",MAX(0,E85-G85)) | I85: =IF(B85="","",F85-H85)
A86: =IF(B86="","","PG"&TEXT(ROW()-1,"0000")) | C86: =IF(B86="","",INDEX(Prestamos!$B:$B,MATCH(B86,Prestamos!$A:$A,0))) | F86: =IF(B86="","",INDEX(Prestamos!$D:$D,MATCH(B86,Prestamos!$A:$A,0))-SUMIFS($H$1:H1,$B$1:B1,B86)) | G86: =IF(B86="","",F86*INDEX(Prestamos!$E:$E,MATCH(B86,Prestamos!$A:$A,0))) | H86: =IF(B86="","",MAX(0,E86-G86)) | I86: =IF(B86="","",F86-H86)
A87: =IF(B87="","","PG"&TEXT(ROW()-1,"0000")) | C87: =IF(B87="","",INDEX(Prestamos!$B:$B,MATCH(B87,Prestamos!$A:$A,0))) | F87: =IF(B87="","",INDEX(Prestamos!$D:$D,MATCH(B87,Prestamos!$A:$A,0))-SUMIFS($H$1:H1,$B$1:B1,B87)) | G87: =IF(B87="","",F87*INDEX(Prestamos!$E:$E,MATCH(B87,Prestamos!$A:$A,0))) | H87: =IF(B87="","",MAX(0,E87-G87)) | I87: =IF(B87="","",F87-H87)
A88: =IF(B88="","","PG"&TEXT(ROW()-1,"0000")) | C88: =IF(B88="","",INDEX(Prestamos!$B:$B,MATCH(B88,Prestamos!$A:$A,0))) | F88: =IF(B88="","",INDEX(Prestamos!$D:$D,MATCH(B88,Prestamos!$A:$A,0))-SUMIFS($H$1:H1,$B$1:B1,B88)) | G88: =IF(B88="","",F88*INDEX(Prestamos!$E:$E,MATCH(B88,Prestamos!$A:$A,0))) | H88: =IF(B88="","",MAX(0,E88-G88)) | I88: =IF(B88="","",F88-H88)
A89: =IF(B89="","","PG"&TEXT(ROW()-1,"0000")) | C89: =IF(B89="","",INDEX(Prestamos!$B:$B,MATCH(B89,Prestamos!$A:$A,0))) | F89: =IF(B89="","",INDEX(Prestamos!$D:$D,MATCH(B89,Prestamos!$A:$A,0))-SUMIFS($H$1:H1,$B$1:B1,B89)) | G89: =IF(B89="","",F89*INDEX(Prestamos!$E:$E,MATCH(B89,Prestamos!$A:$A,0))) | H89: =IF(B89="","",MAX(0,E89-G89)) | I89: =IF(B89="","",F89-H89)
A90: =IF(B90="","","PG"&TEXT(ROW()-1,"0000")) | C90: =IF(B90="","",INDEX(Prestamos!$B:$B,MATCH(B90,Prestamos!$A:$A,0))) | F90: =IF(B90="","",INDEX(Prestamos!$D:$D,MATCH(B90,Prestamos!$A:$A,0))-SUMIFS($H$1:H1,$B$1:B1,B90)) | G90: =IF(B90="","",F90*INDEX(Prestamos!$E:$E,MATCH(B90,Prestamos!$A:$A,0))) | H90: =IF(B90="","",MAX(0,E90-G90)) | I90: =IF(B90="","",F90-H90)
A91: =IF(B91="","","PG"&TEXT(ROW()-1,"0000")) | C91: =IF(B91="","",INDEX(Prestamos!$B:$B,MATCH(B91,Prestamos!$A:$A,0))) | F91: =IF(B91="","",INDEX(Prestamos!$D:$D,MATCH(B91,Prestamos!$A:$A,0))-SUMIFS($H$1:H1,$B$1:B1,B91)) | G91: =IF(B91="","",F91*INDEX(Prestamos!$E:$E,MATCH(B91,Prestamos!$A:$A,0))) | H91: =IF(B91="","",MAX(0,E91-G91)) | I91: =IF(B91="","",F91-H91)
A92: =IF(B92="","","PG"&TEXT(ROW()-1,"0000")) | C92: =IF(B92="","",INDEX(Prestamos!$B:$B,MATCH(B92,Prestamos!$A:$A,0))) | F92: =IF(B92="","",INDEX(Prestamos!$D:$D,MATCH(B92,Prestamos!$A:$A,0))-SUMIFS($H$1:H1,$B$1:B1,B92)) | G92: =IF(B92="","",F92*INDEX(Prestamos!$E:$E,MATCH(B92,Prestamos!$A:$A,0))) | H92: =IF(B92="","",MAX(0,E92-G92)) | I92: =IF(B92="","",F92-H92)
A93: =IF(B93="","","PG"&TEXT(ROW()-1,"0000")) | C93: =IF(B93="","",INDEX(Prestamos!$B:$B,MATCH(B93,Prestamos!$A:$A,0))) | F93: =IF(B93="","",INDEX(Prestamos!$D:$D,MATCH(B93,Prestamos!$A:$A,0))-SUMIFS($H$1:H1,$B$1:B1,B93)) | G93: =IF(B93="","",F93*INDEX(Prestamos!$E:$E,MATCH(B93,Prestamos!$A:$A,0))) | H93: =IF(B93="","",MAX(0,E93-G93)) | I93: =IF(B93="","",F93-H93)
A94: =IF(B94="","","PG"&TEXT(ROW()-1,"0000")) | C94: =IF(B94="","",INDEX(Prestamos!$B:$B,MATCH(B94,Prestamos!$A:$A,0))) | F94: =IF(B94="","",INDEX(Prestamos!$D:$D,MATCH(B94,Prestamos!$A:$A,0))-SUMIFS($H$1:H1,$B$1:B1,B94)) | G94: =IF(B94="","",F94*INDEX(Prestamos!$E:$E,MATCH(B94,Prestamos!$A:$A,0))) | H94: =IF(B94="","",MAX(0,E94-G94)) | I94: =IF(B94="","",F94-H94)
A95: =IF(B95="","","PG"&TEXT(ROW()-1,"0000")) | C95: =IF(B95="","",INDEX(Prestamos!$B:$B,MATCH(B95,Prestamos!$A:$A,0))) | F95: =IF(B95="","",INDEX(Prestamos!$D:$D,MATCH(B95,Prestamos!$A:$A,0))-SUMIFS($H$1:H1,$B$1:B1,B95)) | G95: =IF(B95="","",F95*INDEX(Prestamos!$E:$E,MATCH(B95,Prestamos!$A:$A,0))) | H95: =IF(B95="","",MAX(0,E95-G95)) | I95: =IF(B95="","",F95-H95)
A96: =IF(B96="","","PG"&TEXT(ROW()-1,"0000")) | C96: =IF(B96="","",INDEX(Prestamos!$B:$B,MATCH(B96,Prestamos!$A:$A,0))) | F96: =IF(B96="","",INDEX(Prestamos!$D:$D,MATCH(B96,Prestamos!$A:$A,0))-SUMIFS($H$1:H1,$B$1:B1,B96)) | G96: =IF(B96="","",F96*INDEX(Prestamos!$E:$E,MATCH(B96,Prestamos!$A:$A,0))) | H96: =IF(B96="","",MAX(0,E96-G96)) | I96: =IF(B96="","",F96-H96)
A97: =IF(B97="","","PG"&TEXT(ROW()-1,"0000")) | C97: =IF(B97="","",INDEX(Prestamos!$B:$B,MATCH(B97,Prestamos!$A:$A,0))) | F97: =IF(B97="","",INDEX(Prestamos!$D:$D,MATCH(B97,Prestamos!$A:$A,0))-SUMIFS($H$1:H1,$B$1:B1,B97)) | G97: =IF(B97="","",F97*INDEX(Prestamos!$E:$E,MATCH(B97,Prestamos!$A:$A,0))) | H97: =IF(B97="","",MAX(0,E97-G97)) | I97: =IF(B97="","",F97-H97)
A98: =IF(B98="","","PG"&TEXT(ROW()-1,"0000")) | C98: =IF(B98="","",INDEX(Prestamos!$B:$B,MATCH(B98,Prestamos!$A:$A,0))) | F98: =IF(B98="","",INDEX(Prestamos!$D:$D,MATCH(B98,Prestamos!$A:$A,0))-SUMIFS($H$1:H1,$B$1:B1,B98)) | G98: =IF(B98="","",F98*INDEX(Prestamos!$E:$E,MATCH(B98,Prestamos!$A:$A,0))) | H98: =IF(B98="","",MAX(0,E98-G98)) | I98: =IF(B98="","",F98-H98)
A99: =IF(B99="","","PG"&TEXT(ROW()-1,"0000")) | C99: =IF(B99="","",INDEX(Prestamos!$B:$B,MATCH(B99,Prestamos!$A:$A,0))) | F99: =IF(B99="","",INDEX(Prestamos!$D:$D,MATCH(B99,Prestamos!$A:$A,0))-SUMIFS($H$1:H1,$B$1:B1,B99)) | G99: =IF(B99="","",F99*INDEX(Prestamos!$E:$E,MATCH(B99,Prestamos!$A:$A,0))) | H99: =IF(B99="","",MAX(0,E99-G99)) | I99: =IF(B99="","",F99-H99)
A100: =IF(B100="","","PG"&TEXT(ROW()-1,"0000")) | C100: =IF(B100="","",INDEX(Prestamos!$B:$B,MATCH(B100,Prestamos!$A:$A,0))) | F100: =IF(B100="","",INDEX(Prestamos!$D:$D,MATCH(B100,Prestamos!$A:$A,0))-SUMIFS($H$1:H1,$B$1:B1,B100)) | G100: =IF(B100="","",F100*INDEX(Prestamos!$E:$E,MATCH(B100,Prestamos!$A:$A,0))) | H100: =IF(B100="","",MAX(0,E100-G100)) | I100: =IF(B100="","",F100-H100)
...
